[
  {
    "component": "blockchain",
    "slug": "134",
    "title": "Nomos P2P Network Bootstrapping Specification",
    "status": "raw",
    "category": "networking",
    "updated": "2026-01-22",
    "path": "blockchain/raw/p2p-network-bootstrapping.html",
    "archived": false
  },
  {
    "component": "blockchain",
    "slug": "135",
    "title": "Nomos P2P Network Specification",
    "status": "draft",
    "category": "networking",
    "updated": "2026-01-22",
    "path": "blockchain/raw/p2p-network.html",
    "archived": false
  },
  {
    "component": "blockchain",
    "slug": "136",
    "title": "NomosDA Network",
    "status": "raw",
    "category": "unspecified",
    "updated": "2026-01-22",
    "path": "blockchain/raw/nomosda-network.html",
    "archived": false
  },
  {
    "component": "blockchain",
    "slug": "137",
    "title": "Nomos p2p Network Hardware Requirements Specification",
    "status": "raw",
    "category": "infrastructure",
    "updated": "2026-01-22",
    "path": "blockchain/raw/p2p-hardware-requirements.html",
    "archived": false
  },
  {
    "component": "blockchain",
    "slug": "138",
    "title": "Nomos P2P Network NAT Solution Specification",
    "status": "raw",
    "category": "networking",
    "updated": "2026-01-22",
    "path": "blockchain/raw/p2p-nat-solution.html",
    "archived": false
  },
  {
    "component": "blockchain",
    "slug": "139",
    "title": "NomosDA Encoding Protocol",
    "status": "raw",
    "category": "unspecified",
    "updated": "2026-01-22",
    "path": "blockchain/raw/nomosda-encoding.html",
    "archived": false
  },
  {
    "component": "blockchain",
    "slug": "140",
    "title": "Claro Consensus Protocol",
    "status": "deprecated",
    "category": "Standards Track",
    "updated": "2026-01-22",
    "path": "blockchain/deprecated/claro.html",
    "archived": false
  },
  {
    "component": "blockchain",
    "slug": "83",
    "title": "Cryptarchia Proof of Leadership Specification",
    "status": "raw",
    "category": "Standards Track",
    "updated": "2026-01-22",
    "path": "blockchain/raw/cryptarchia-proof-of-leadership.html",
    "archived": false
  },
  {
    "component": "blockchain",
    "slug": "84",
    "title": "Nomos Key Types and Generation",
    "status": "raw",
    "category": "Standards Track",
    "updated": "2026-01-22",
    "path": "blockchain/raw/nomos-key-types-and-generation.html",
    "archived": false
  },
  {
    "component": "blockchain",
    "slug": "85",
    "title": "Bedrock Anonymous Leaders Reward Protocol",
    "status": "raw",
    "category": "Standards Track",
    "updated": "2026-01-22",
    "path": "blockchain/raw/bedrock-anonymous-leaders-reward.html",
    "archived": false
  },
  {
    "component": "blockchain",
    "slug": "86",
    "title": "Bedrock v1.2 Service Reward Distribution Protocol",
    "status": "raw",
    "category": "Standards Track",
    "updated": "2026-01-22",
    "path": "blockchain/raw/bedrock-service-reward-distribution.html",
    "archived": false
  },
  {
    "component": "blockchain",
    "slug": "87",
    "title": "Bedrock Service Declaration Protocol",
    "status": "raw",
    "category": "Standards Track",
    "updated": "2026-01-22",
    "path": "blockchain/raw/bedrock-service-declaration-protocol.html",
    "archived": false
  },
  {
    "component": "blockchain",
    "slug": "88",
    "title": "Nomos Proof of Quota Specification",
    "status": "raw",
    "category": "Standards Track",
    "updated": "2026-01-22",
    "path": "blockchain/raw/nomos-proof-of-quota.html",
    "archived": false
  },
  {
    "component": "blockchain",
    "slug": "89",
    "title": "Nomos Message Formatting Specification",
    "status": "raw",
    "category": "Standards Track",
    "updated": "2026-01-22",
    "path": "blockchain/raw/nomos-message-formatting.html",
    "archived": false
  },
  {
    "component": "blockchain",
    "slug": "90",
    "title": "Bedrock Genesis Block Specification",
    "status": "raw",
    "category": "Standards Track",
    "updated": "2026-01-22",
    "path": "blockchain/raw/bedrock-genesis-block.html",
    "archived": false
  },
  {
    "component": "blockchain",
    "slug": "91",
    "title": "Nomos Message Encapsulation Mechanism",
    "status": "raw",
    "category": "Standards Track",
    "updated": "2026-01-22",
    "path": "blockchain/raw/nomos-message-encapsulation.html",
    "archived": false
  },
  {
    "component": "blockchain",
    "slug": "92",
    "title": "Nomos Cryptarchia v1 Protocol Specification",
    "status": "raw",
    "category": "Standards Track",
    "updated": "2026-01-22",
    "path": "blockchain/raw/nomos-cryptarchia-v1-protocol.html",
    "archived": false
  },
  {
    "component": "blockchain",
    "slug": "93",
    "title": "Bedrock v1.1 Block Construction, Validation and Execution Specification",
    "status": "raw",
    "category": "Standards Track",
    "updated": "2026-01-22",
    "path": "blockchain/raw/bedrock-v1.1-block-construction.html",
    "archived": false
  },
  {
    "component": "blockchain",
    "slug": "94",
    "title": "Cryptarchia Total Stake Inference",
    "status": "raw",
    "category": "Standards Track",
    "updated": "2026-01-22",
    "path": "blockchain/raw/cryptarchia-total-stake-inference.html",
    "archived": false
  },
  {
    "component": "blockchain",
    "slug": "95",
    "title": "Nomos Blend Protocol",
    "status": "raw",
    "category": "Standards Track",
    "updated": "2026-01-22",
    "path": "blockchain/raw/nomos-blend-protocol.html",
    "archived": false
  },
  {
    "component": "blockchain",
    "slug": "96",
    "title": "Cryptarchia v1 Bootstrapping & Synchronization",
    "status": "raw",
    "category": "Standards Track",
    "updated": "2026-01-22",
    "path": "blockchain/raw/cryptarchia-v1-bootstr-sync.html",
    "archived": false
  },
  {
    "component": "blockchain",
    "slug": "97",
    "title": "Nomos Payload Formatting Specification",
    "status": "raw",
    "category": "Standards Track",
    "updated": "2026-01-22",
    "path": "blockchain/raw/nomos-payload-formatting.html",
    "archived": false
  },
  {
    "component": "blockchain",
    "slug": "98",
    "title": "Bedrock v1.1 Mantle Specification",
    "status": "raw",
    "category": "Informational",
    "updated": "2026-01-22",
    "path": "blockchain/raw/bedrock-v1.1-mantle-specification.html",
    "archived": false
  },
  {
    "component": "ift-ts",
    "slug": "1",
    "title": "Consensus-Oriented Specification System",
    "status": "draft",
    "category": "Best Current Practice",
    "updated": "2026-01-22",
    "path": "ift-ts/raw/1/coss.html",
    "archived": false
  },
  {
    "component": "ift-ts",
    "slug": "100",
    "title": "Interep as group management for RLN",
    "status": "raw",
    "category": "unspecified",
    "updated": "2026-01-22",
    "path": "ift-ts/raw/rln-interep-spec.html",
    "archived": false
  },
  {
    "component": "ift-ts",
    "slug": "101",
    "title": "Secure channel setup using decentralized MLS and Ethereum accounts",
    "status": "raw",
    "category": "Standards Track",
    "updated": "2026-01-22",
    "path": "ift-ts/raw/eth-mls-onchain.html",
    "archived": false
  },
  {
    "component": "ift-ts",
    "slug": "102",
    "title": "RLN Stealth Commitment Usage",
    "status": "raw",
    "category": "Standards Track",
    "updated": "2026-01-22",
    "path": "ift-ts/raw/rln-stealth-commitments.html",
    "archived": false
  },
  {
    "component": "ift-ts",
    "slug": "103",
    "title": "Decentralized Key and Session Setup for Secure Messaging over Ethereum",
    "status": "raw",
    "category": "informational",
    "updated": "2026-01-22",
    "path": "ift-ts/raw/decentralized-messaging-ethereum.html",
    "archived": false
  },
  {
    "component": "ift-ts",
    "slug": "104",
    "title": "Secure channel setup using decentralized MLS and Ethereum accounts",
    "status": "raw",
    "category": "Standards Track",
    "updated": "2026-01-22",
    "path": "ift-ts/raw/eth-mls-offchain.html",
    "archived": false
  },
  {
    "component": "ift-ts",
    "slug": "105",
    "title": "Gossipsub Tor Push",
    "status": "raw",
    "category": "Standards Track",
    "updated": "2026-01-22",
    "path": "ift-ts/raw/gossipsub-tor-push.html",
    "archived": false
  },
  {
    "component": "ift-ts",
    "slug": "106",
    "title": "Rate Limit Nullifier V2",
    "status": "raw",
    "category": "unspecified",
    "updated": "2026-01-22",
    "path": "ift-ts/raw/rln-v2.html",
    "archived": false
  },
  {
    "component": "ift-ts",
    "slug": "107",
    "title": "Logos Capability Discovery Protocol",
    "status": "raw",
    "category": "Standards Track",
    "updated": "2026-01-22",
    "path": "ift-ts/raw/logos-capability-discovery.html",
    "archived": false
  },
  {
    "component": "ift-ts",
    "slug": "108",
    "title": "Secure 1-to-1 channel setup using X3DH and the double ratchet",
    "status": "raw",
    "category": "Standards Track",
    "updated": "2026-01-22",
    "path": "ift-ts/raw/noise-x3dh-double-ratchet.html",
    "archived": false
  },
  {
    "component": "ift-ts",
    "slug": "109",
    "title": "Scalable Data Sync protocol for distributed logs",
    "status": "raw",
    "category": "Standards Track",
    "updated": "2026-01-22",
    "path": "ift-ts/raw/sds.html",
    "archived": false
  },
  {
    "component": "ift-ts",
    "slug": "110",
    "title": "Secure channel setup using Ethereum accounts",
    "status": "deleted",
    "category": "Standards Track",
    "updated": "2026-01-22",
    "path": "ift-ts/raw/deleted/eth-secpm.html",
    "archived": false
  },
  {
    "component": "ift-ts",
    "slug": "141",
    "title": "Multi-message_id burn feature RLN",
    "status": "raw",
    "category": "Standards Track",
    "updated": "2026-01-22",
    "path": "ift-ts/raw/multi-message_id-burn-rln.html",
    "archived": false
  },
  {
    "component": "ift-ts",
    "slug": "142",
    "title": "Zerokit API",
    "status": "raw",
    "category": "Standards Track",
    "updated": "2026-01-22",
    "path": "ift-ts/raw/zerokit-api.html",
    "archived": false
  },
  {
    "component": "ift-ts",
    "slug": "143",
    "title": "Extended Kademlia Discovery with capability filtering",
    "status": "raw",
    "category": "Standards Track",
    "updated": "2026-01-26",
    "path": "ift-ts/raw/extended-kad-disco.html",
    "archived": false
  },
  {
    "component": "ift-ts",
    "slug": "2",
    "title": "Minimum Viable Data Synchronization",
    "status": "stable",
    "category": "unspecified",
    "updated": "2026-01-22",
    "path": "ift-ts/raw/2/mvds.html",
    "archived": false
  },
  {
    "component": "ift-ts",
    "slug": "25",
    "title": "Libp2p Peer Discovery via DNS",
    "status": "deleted",
    "category": "unspecified",
    "updated": "2026-01-22",
    "path": "ift-ts/raw/25/libp2p-dns-discovery.html",
    "archived": false
  },
  {
    "component": "ift-ts",
    "slug": "3",
    "title": "Remote log specification",
    "status": "draft",
    "category": "unspecified",
    "updated": "2026-01-22",
    "path": "ift-ts/raw/3/remote-log.html",
    "archived": false
  },
  {
    "component": "ift-ts",
    "slug": "32",
    "title": "Rate Limit Nullifier",
    "status": "draft",
    "category": "unspecified",
    "updated": "2026-01-22",
    "path": "ift-ts/raw/32/rln-v1.html",
    "archived": false
  },
  {
    "component": "ift-ts",
    "slug": "4",
    "title": "MVDS Metadata Field",
    "status": "draft",
    "category": "unspecified",
    "updated": "2026-01-22",
    "path": "ift-ts/raw/4/mvds-meta.html",
    "archived": false
  },
  {
    "component": "ift-ts",
    "slug": "72",
    "title": "RFC Template",
    "status": "raw/draft/stable/deprecated",
    "category": "Standards Track/Informational/Best Current Practice",
    "updated": "2026-01-19",
    "path": "ift-ts/template.html",
    "archived": false
  },
  {
    "component": "ift-ts",
    "slug": "73",
    "title": "Hashgraphlike Consensus Protocol",
    "status": "raw",
    "category": "Standards Track",
    "updated": "2026-01-22",
    "path": "ift-ts/raw/consensus-hashgraphlike.html",
    "archived": false
  },
  {
    "component": "ift-ts",
    "slug": "74",
    "title": "Extensible Peer Records",
    "status": "raw",
    "category": "Standards Track",
    "updated": "2026-01-24",
    "path": "ift-ts/raw/extensible-peer-records.html",
    "archived": false
  },
  {
    "component": "ift-ts",
    "slug": "99",
    "title": "LIBP2P-MIX",
    "status": "raw",
    "category": "Standards Track",
    "updated": "2026-01-22",
    "path": "ift-ts/raw/mix.html",
    "archived": false
  },
  {
    "component": "ift-ts",
    "slug": "mix-spam-protection-rln",
    "title": "mix-spam-protection-rln",
    "status": "unknown",
    "category": "unspecified",
    "updated": "2026-01-24",
    "path": "ift-ts/raw/mix-spam-protection-rln.html",
    "archived": false
  },
  {
    "component": "messaging",
    "slug": "10",
    "title": "Waku v2",
    "status": "draft",
    "category": "unspecified",
    "updated": "2026-01-22",
    "path": "messaging/standards/core/10/waku2.html",
    "archived": false
  },
  {
    "component": "messaging",
    "slug": "11",
    "title": "Waku v2 Relay",
    "status": "stable",
    "category": "unspecified",
    "updated": "2026-01-22",
    "path": "messaging/standards/core/11/relay.html",
    "archived": false
  },
  {
    "component": "messaging",
    "slug": "12",
    "title": "Waku v2 Filter",
    "status": "draft",
    "category": "unspecified",
    "updated": "2026-01-22",
    "path": "messaging/standards/core/12/filter.html",
    "archived": false
  },
  {
    "component": "messaging",
    "slug": "13",
    "title": "Waku Store Query",
    "status": "draft",
    "category": "unspecified",
    "updated": "2026-01-22",
    "path": "messaging/standards/core/13/store.html",
    "archived": false
  },
  {
    "component": "messaging",
    "slug": "14",
    "title": "Waku v2 Message",
    "status": "stable",
    "category": "Standards Track",
    "updated": "2026-01-22",
    "path": "messaging/standards/core/14/message.html",
    "archived": false
  },
  {
    "component": "messaging",
    "slug": "15",
    "title": "Waku Bridge",
    "status": "draft",
    "category": "unspecified",
    "updated": "2026-01-22",
    "path": "messaging/standards/core/15/bridge.html",
    "archived": false
  },
  {
    "component": "messaging",
    "slug": "16",
    "title": "Waku v2 RPC API",
    "status": "deprecated",
    "category": "unspecified",
    "updated": "2026-01-22",
    "path": "messaging/deprecated/16/rpc.html",
    "archived": false
  },
  {
    "component": "messaging",
    "slug": "17",
    "title": "Waku v2 RLN Relay",
    "status": "draft",
    "category": "unspecified",
    "updated": "2026-01-22",
    "path": "messaging/standards/core/17/rln-relay.html",
    "archived": false
  },
  {
    "component": "messaging",
    "slug": "18",
    "title": "Waku SWAP Accounting",
    "status": "deprecated",
    "category": "unspecified",
    "updated": "2026-01-22",
    "path": "messaging/deprecated/18/swap.html",
    "archived": false
  },
  {
    "component": "messaging",
    "slug": "19",
    "title": "Waku v2 Light Push",
    "status": "draft",
    "category": "unspecified",
    "updated": "2026-01-22",
    "path": "messaging/standards/core/19/lightpush.html",
    "archived": false
  },
  {
    "component": "messaging",
    "slug": "20",
    "title": "Toy Ethereum Private Message",
    "status": "draft",
    "category": "unspecified",
    "updated": "2026-01-22",
    "path": "messaging/standards/application/20/toy-eth-pm.html",
    "archived": false
  },
  {
    "component": "messaging",
    "slug": "21",
    "title": "Waku v2 Fault-Tolerant Store",
    "status": "deleted",
    "category": "unspecified",
    "updated": "2026-01-22",
    "path": "messaging/deprecated/fault-tolerant-store.html",
    "archived": false
  },
  {
    "component": "messaging",
    "slug": "22",
    "title": "Waku v2 Toy Chat",
    "status": "draft",
    "category": "unspecified",
    "updated": "2026-01-22",
    "path": "messaging/informational/22/toy-chat.html",
    "archived": false
  },
  {
    "component": "messaging",
    "slug": "23",
    "title": "Waku v2 Topic Usage Recommendations",
    "status": "draft",
    "category": "Informational",
    "updated": "2026-01-22",
    "path": "messaging/informational/23/topics.html",
    "archived": false
  },
  {
    "component": "messaging",
    "slug": "26",
    "title": "Waku Message Payload Encryption",
    "status": "draft",
    "category": "unspecified",
    "updated": "2026-01-22",
    "path": "messaging/standards/application/26/payload.html",
    "archived": false
  },
  {
    "component": "messaging",
    "slug": "27",
    "title": "Waku v2 Client Peer Management Recommendations",
    "status": "draft",
    "category": "unspecified",
    "updated": "2026-01-22",
    "path": "messaging/informational/27/peers.html",
    "archived": false
  },
  {
    "component": "messaging",
    "slug": "29",
    "title": "Waku v2 Client Parameter Configuration Recommendations",
    "status": "draft",
    "category": "unspecified",
    "updated": "2026-01-22",
    "path": "messaging/informational/29/config.html",
    "archived": false
  },
  {
    "component": "messaging",
    "slug": "30",
    "title": "Adaptive nodes",
    "status": "draft",
    "category": "unspecified",
    "updated": "2026-01-22",
    "path": "messaging/informational/30/adaptive-nodes.html",
    "archived": false
  },
  {
    "component": "messaging",
    "slug": "31",
    "title": "Waku v2 usage of ENR",
    "status": "draft",
    "category": "unspecified",
    "updated": "2026-01-22",
    "path": "messaging/standards/core/31/enr.html",
    "archived": false
  },
  {
    "component": "messaging",
    "slug": "33",
    "title": "Waku v2 Discv5 Ambient Peer Discovery",
    "status": "draft",
    "category": "unspecified",
    "updated": "2026-01-22",
    "path": "messaging/standards/core/33/discv5.html",
    "archived": false
  },
  {
    "component": "messaging",
    "slug": "34",
    "title": "Waku2 Peer Exchange",
    "status": "draft",
    "category": "Standards Track",
    "updated": "2026-01-22",
    "path": "messaging/standards/core/34/peer-exchange.html",
    "archived": false
  },
  {
    "component": "messaging",
    "slug": "36",
    "title": "Waku v2 C Bindings API",
    "status": "draft",
    "category": "unspecified",
    "updated": "2026-01-22",
    "path": "messaging/standards/core/36/bindings-api.html",
    "archived": false
  },
  {
    "component": "messaging",
    "slug": "5",
    "title": "Waku v0",
    "status": "deprecated",
    "category": "unspecified",
    "updated": "2026-01-22",
    "path": "messaging/deprecated/5/waku0.html",
    "archived": false
  },
  {
    "component": "messaging",
    "slug": "53",
    "title": "X3DH usage for Waku payload encryption",
    "status": "draft",
    "category": "Standards Track",
    "updated": "2026-01-22",
    "path": "messaging/standards/application/53/x3dh.html",
    "archived": false
  },
  {
    "component": "messaging",
    "slug": "54",
    "title": "Session management for Waku X3DH",
    "status": "draft",
    "category": "Standards Track",
    "updated": "2026-01-22",
    "path": "messaging/standards/application/54/x3dh-sessions.html",
    "archived": false
  },
  {
    "component": "messaging",
    "slug": "6",
    "title": "Waku v1",
    "status": "stable",
    "category": "unspecified",
    "updated": "2026-01-22",
    "path": "messaging/standards/legacy/6/waku1.html",
    "archived": false
  },
  {
    "component": "messaging",
    "slug": "64",
    "title": "Waku v2 Network",
    "status": "draft",
    "category": "Best Current Practice",
    "updated": "2026-01-22",
    "path": "messaging/standards/core/64/network.html",
    "archived": false
  },
  {
    "component": "messaging",
    "slug": "66",
    "title": "Waku Metadata Protocol",
    "status": "draft",
    "category": "unspecified",
    "updated": "2026-01-22",
    "path": "messaging/standards/core/66/metadata.html",
    "archived": false
  },
  {
    "component": "messaging",
    "slug": "7",
    "title": "Waku Envelope data field",
    "status": "stable",
    "category": "unspecified",
    "updated": "2026-01-22",
    "path": "messaging/standards/legacy/7/data.html",
    "archived": false
  },
  {
    "component": "messaging",
    "slug": "8",
    "title": "Waku Mailserver",
    "status": "stable",
    "category": "unspecified",
    "updated": "2026-01-22",
    "path": "messaging/standards/legacy/8/mail.html",
    "archived": false
  },
  {
    "component": "messaging",
    "slug": "9",
    "title": "Waku RPC API",
    "status": "stable",
    "category": "unspecified",
    "updated": "2026-01-22",
    "path": "messaging/standards/legacy/9/rpc.html",
    "archived": false
  },
  {
    "component": "status",
    "slug": "112",
    "title": "Status URL Data",
    "status": "raw",
    "category": "Standards Track",
    "updated": "2026-01-22",
    "path": "archived/status/raw/url-data.html",
    "archived": true
  },
  {
    "component": "status",
    "slug": "113",
    "title": "Status Protocol Stack",
    "status": "raw",
    "category": "Standards Track",
    "updated": "2026-01-22",
    "path": "archived/status/raw/status-app-protocols.html",
    "archived": true
  },
  {
    "component": "status",
    "slug": "114",
    "title": "Status URL Scheme",
    "status": "raw",
    "category": "Standards Track",
    "updated": "2026-01-22",
    "path": "archived/status/raw/url-scheme.html",
    "archived": true
  },
  {
    "component": "status",
    "slug": "115",
    "title": "Status Simple Scaling",
    "status": "raw",
    "category": "Informational",
    "updated": "2026-01-22",
    "path": "archived/status/raw/simple-scaling.html",
    "archived": true
  },
  {
    "component": "status",
    "slug": "116",
    "title": "MVDS Usage in Status",
    "status": "raw",
    "category": "Best Current Practice",
    "updated": "2026-01-22",
    "path": "archived/status/raw/status-mvds.html",
    "archived": true
  },
  {
    "component": "status",
    "slug": "117",
    "title": "IPFS gateway for Sticker Pack",
    "status": "deprecated",
    "category": "unspecified",
    "updated": "2026-01-22",
    "path": "archived/status/deprecated/IPFS-gateway-for-sticker-Pack.html",
    "archived": true
  },
  {
    "component": "status",
    "slug": "118",
    "title": "Waku Mailserver",
    "status": "deprecated",
    "category": "unspecified",
    "updated": "2026-01-22",
    "path": "archived/status/deprecated/waku-mailserver.html",
    "archived": true
  },
  {
    "component": "status",
    "slug": "119",
    "title": "Secure Transport",
    "status": "deprecated",
    "category": "unspecified",
    "updated": "2026-01-22",
    "path": "archived/status/deprecated/secure-transport.html",
    "archived": true
  },
  {
    "component": "status",
    "slug": "120",
    "title": "Group Chat",
    "status": "deprecated",
    "category": "unspecified",
    "updated": "2026-01-22",
    "path": "archived/status/deprecated/group-chat.html",
    "archived": true
  },
  {
    "component": "status",
    "slug": "121",
    "title": "Payloads",
    "status": "deprecated",
    "category": "unspecified",
    "updated": "2026-01-22",
    "path": "archived/status/deprecated/payloads.html",
    "archived": true
  },
  {
    "component": "status",
    "slug": "122",
    "title": "3rd party",
    "status": "deprecated",
    "category": "unspecified",
    "updated": "2026-01-22",
    "path": "archived/status/deprecated/3rd-party.html",
    "archived": true
  },
  {
    "component": "status",
    "slug": "123",
    "title": "Client",
    "status": "deprecated",
    "category": "unspecified",
    "updated": "2026-01-22",
    "path": "archived/status/deprecated/client.html",
    "archived": true
  },
  {
    "component": "status",
    "slug": "124",
    "title": "Waku Usage",
    "status": "deprecated",
    "category": "unspecified",
    "updated": "2026-01-22",
    "path": "archived/status/deprecated/waku-usage.html",
    "archived": true
  },
  {
    "component": "status",
    "slug": "125",
    "title": "Status interactions with the Ethereum blockchain",
    "status": "deprecated",
    "category": "unspecified",
    "updated": "2026-01-22",
    "path": "archived/status/deprecated/ethereum-usage.html",
    "archived": true
  },
  {
    "component": "status",
    "slug": "126",
    "title": "Dapp browser API usage",
    "status": "deprecated",
    "category": "unspecified",
    "updated": "2026-01-22",
    "path": "archived/status/deprecated/dapp-browser-API-usage.html",
    "archived": true
  },
  {
    "component": "status",
    "slug": "127",
    "title": "Whisper mailserver",
    "status": "deprecated",
    "category": "unspecified",
    "updated": "2026-01-22",
    "path": "archived/status/deprecated/whisper-mailserver.html",
    "archived": true
  },
  {
    "component": "status",
    "slug": "128",
    "title": "EIPS",
    "status": "deprecated",
    "category": "unspecified",
    "updated": "2026-01-22",
    "path": "archived/status/deprecated/eips.html",
    "archived": true
  },
  {
    "component": "status",
    "slug": "129",
    "title": "Keycard Usage for Wallet and Chat Keys",
    "status": "deprecated",
    "category": "unspecified",
    "updated": "2026-01-22",
    "path": "archived/status/deprecated/keycard-usage-for-wallet-and-chat-keys.html",
    "archived": true
  },
  {
    "component": "status",
    "slug": "130",
    "title": "Notifications",
    "status": "deprecated",
    "category": "unspecified",
    "updated": "2026-01-22",
    "path": "archived/status/deprecated/notifications.html",
    "archived": true
  },
  {
    "component": "status",
    "slug": "131",
    "title": "Whisper Usage",
    "status": "deprecated",
    "category": "unspecified",
    "updated": "2026-01-22",
    "path": "archived/status/deprecated/whisper-usage.html",
    "archived": true
  },
  {
    "component": "status",
    "slug": "132",
    "title": "Account",
    "status": "deprecated",
    "category": "unspecified",
    "updated": "2026-01-22",
    "path": "archived/status/deprecated/account.html",
    "archived": true
  },
  {
    "component": "status",
    "slug": "133",
    "title": "Push notification server",
    "status": "deprecated",
    "category": "unspecified",
    "updated": "2026-01-22",
    "path": "archived/status/deprecated/push-notification-server.html",
    "archived": true
  },
  {
    "component": "status",
    "slug": "24",
    "title": "Status Community Directory Curation Voting using Waku v2",
    "status": "draft",
    "category": "unspecified",
    "updated": "2026-01-22",
    "path": "archived/status/24/curation.html",
    "archived": true
  },
  {
    "component": "status",
    "slug": "28",
    "title": "Status community featuring using waku v2",
    "status": "draft",
    "category": "unspecified",
    "updated": "2026-01-22",
    "path": "archived/status/28/featuring.html",
    "archived": true
  },
  {
    "component": "status",
    "slug": "55",
    "title": "Status 1-to-1 Chat",
    "status": "draft",
    "category": "Standards Track",
    "updated": "2026-01-22",
    "path": "archived/status/55/1to1-chat.html",
    "archived": true
  },
  {
    "component": "status",
    "slug": "56",
    "title": "Status Communities that run over Waku v2",
    "status": "draft",
    "category": "Standards Track",
    "updated": "2026-01-22",
    "path": "archived/status/56/communities.html",
    "archived": true
  },
  {
    "component": "status",
    "slug": "61",
    "title": "Status Community History Service",
    "status": "draft",
    "category": "Standards Track",
    "updated": "2026-01-22",
    "path": "archived/status/61/community-history-service.html",
    "archived": true
  },
  {
    "component": "status",
    "slug": "62",
    "title": "Status Message Payloads",
    "status": "draft",
    "category": "unspecified",
    "updated": "2026-01-22",
    "path": "archived/status/62/payloads.html",
    "archived": true
  },
  {
    "component": "status",
    "slug": "63",
    "title": "Status Keycard Usage",
    "status": "draft",
    "category": "Standards Track",
    "updated": "2026-01-22",
    "path": "archived/status/63/keycard-usage.html",
    "archived": true
  },
  {
    "component": "status",
    "slug": "65",
    "title": "Status Account Address",
    "status": "draft",
    "category": "Standards Track",
    "updated": "2026-01-22",
    "path": "archived/status/65/account-address.html",
    "archived": true
  },
  {
    "component": "status",
    "slug": "71",
    "title": "Push Notification Server",
    "status": "draft",
    "category": "Standards Track",
    "updated": "2026-01-22",
    "path": "archived/status/71/push-notification-server.html",
    "archived": true
  },
  {
    "component": "storage",
    "slug": "111",
    "title": "Codex Block Exchange Protocol",
    "status": "raw",
    "category": "Standards Track",
    "updated": "2026-01-22",
    "path": "storage/raw/codex-block-exchange.html",
    "archived": false
  },
  {
    "component": "storage",
    "slug": "75",
    "title": "Codex Discovery",
    "status": "raw",
    "category": "unspecified",
    "updated": "2026-01-22",
    "path": "storage/raw/dht.html",
    "archived": false
  },
  {
    "component": "storage",
    "slug": "76",
    "title": "Codex Community History",
    "status": "raw",
    "category": "unspecified",
    "updated": "2026-01-22",
    "path": "storage/raw/community-history.html",
    "archived": false
  },
  {
    "component": "storage",
    "slug": "77",
    "title": "Codex Storage Marketplace",
    "status": "deprecated",
    "category": "Standards Track",
    "updated": "2026-01-22",
    "path": "storage/deprecated/codex-marketplace.html",
    "archived": false
  },
  {
    "component": "storage",
    "slug": "78",
    "title": "Codex Slot Builder",
    "status": "deprecated",
    "category": "unspecified",
    "updated": "2026-01-22",
    "path": "storage/deprecated/slot-buIlder.html",
    "archived": false
  },
  {
    "component": "storage",
    "slug": "79",
    "title": "Codex Erasue Coding",
    "status": "deprecated",
    "category": "unspecified",
    "updated": "2026-01-22",
    "path": "storage/deprecated/erasure-coding.html",
    "archived": false
  },
  {
    "component": "storage",
    "slug": "80",
    "title": "Codex Store Module",
    "status": "raw",
    "category": "Standards Track",
    "updated": "2026-01-22",
    "path": "storage/raw/codex-store.html",
    "archived": false
  },
  {
    "component": "storage",
    "slug": "81",
    "title": "Codex Prover Module",
    "status": "deprecated",
    "category": "Standards Track",
    "updated": "2026-01-22",
    "path": "storage/deprecated/codex-prover.html",
    "archived": false
  },
  {
    "component": "storage",
    "slug": "82",
    "title": "Codex Merkle Tree",
    "status": "raw",
    "category": "Standards Track",
    "updated": "2026-01-22",
    "path": "storage/raw/codex-merkle-tree.html",
    "archived": false
  }
]